Metadata-Version: 2.4
Name: piprce
Version: 0.2.8.7
Author: lvxianzhi
Requires-Dist: pycryptodome>=3.20.0
Requires-Dist: cffi
Dynamic: author
